__init__.py
pixel.py
pixel_flipdot-0.0.5.dist-info/LICENSE
pixel_flipdot-0.0.5.dist-info/METADATA
pixel_flipdot-0.0.5.dist-info/WHEEL
pixel_flipdot-0.0.5.dist-info/top_level.txt
pixel_flipdot-0.0.5.dist-info/RECORD
