Metadata-Version: 2.1
Name: pixel-flipdot
Version: 0.0.5
Summary: A simple Python package for driving Pixel Bydgoszcz flip-dot displays
Author-email: domints <dominik@szymanski.io>
License: MIT License
Project-URL: Homepage, https://github.com/domints/PixelFlipDot
Project-URL: Issues, https://github.com/domints/PixelFlipDot/issues
Classifier: Development Status :: 3 - Alpha
Classifier: Programming Language :: Python :: 3
Classifier: License :: OSI Approved :: MIT License
Classifier: Operating System :: OS Independent
Requires-Python: >=3.8
License-File: LICENSE
Requires-Dist: pyserial==3.5
Provides-Extra: images
Requires-Dist: numpy==2.1.3; extra == "images"
Requires-Dist: pillow==10.4.0; extra == "images"
Provides-Extra: gpio
Requires-Dist: gpiozero==2.0.1; extra == "gpio"
